futoin_cid-0.9.1-py3.9-nspkg.pth
futoin/cid/__init__.py
futoin/cid/__main__.py
futoin/cid/buildtool.py
futoin/cid/cidtool.py
futoin/cid/cli.py
futoin/cid/coloring.py
futoin/cid/cte.py
futoin/cid/migrationtool.py
futoin/cid/rmstool.py
futoin/cid/runenvtool.py
futoin/cid/runtimetool.py
futoin/cid/subtool.py
futoin/cid/testtool.py
futoin/cid/vcstool.py
futoin/cid/contrib/__init__.py
futoin/cid/contrib/distro.py
futoin/cid/contrib/docopt.py
futoin/cid/details/__init__.py
futoin/cid/details/nginx.py
futoin/cid/details/resourcealgo.py
futoin/cid/misc/__init__.py
futoin/cid/misc/releasetool.py
futoin/cid/mixins/__init__.py
futoin/cid/mixins/config.py
futoin/cid/mixins/data.py
futoin/cid/mixins/deploy.py
futoin/cid/mixins/lock.py
futoin/cid/mixins/log.py
futoin/cid/mixins/ondemand.py
futoin/cid/mixins/service.py
futoin/cid/mixins/tool.py
futoin/cid/tool/__init__.py
futoin/cid/tool/anttool.py
futoin/cid/tool/archivatool.py
futoin/cid/tool/artifactorytool.py
futoin/cid/tool/awstool.py
futoin/cid/tool/bashtool.py
futoin/cid/tool/bashtoolmixin.py
futoin/cid/tool/binutilstool.py
futoin/cid/tool/bowertool.py
futoin/cid/tool/brewtool.py
futoin/cid/tool/bundlermixin.py
futoin/cid/tool/bundlertool.py
futoin/cid/tool/bzip2tool.py
futoin/cid/tool/cargotool.py
futoin/cid/tool/cidtool.py
futoin/cid/tool/cmaketool.py
futoin/cid/tool/composertool.py
futoin/cid/tool/ctesttool.py
futoin/cid/tool/curltool.py
futoin/cid/tool/curltoolmixin.py
futoin/cid/tool/dockercomposetool.py
futoin/cid/tool/dockertool.py
futoin/cid/tool/elixirtool.py
futoin/cid/tool/erlangtool.py
futoin/cid/tool/exetool.py
futoin/cid/tool/flywaytool.py
futoin/cid/tool/futointool.py
futoin/cid/tool/gcctool.py
futoin/cid/tool/gemtool.py
futoin/cid/tool/gemtoolmixin.py
futoin/cid/tool/gittool.py
futoin/cid/tool/gotool.py
futoin/cid/tool/gpgtool.py
futoin/cid/tool/gradletool.py
futoin/cid/tool/grunttool.py
futoin/cid/tool/gulptool.py
futoin/cid/tool/gvmtool.py
futoin/cid/tool/gziptool.py
futoin/cid/tool/hgtool.py
futoin_cid-0.9.1.dist-info/LICENSE
futoin_cid-0.9.1.dist-info/METADATA
futoin_cid-0.9.1.dist-info/WHEEL
futoin_cid-0.9.1.dist-info/entry_points.txt
futoin_cid-0.9.1.dist-info/namespace_packages.txt
futoin_cid-0.9.1.dist-info/top_level.txt
futoin_cid-0.9.1.dist-info/RECORD
