Metadata-Version: 2.1
Name: futoin-cid
Version: 0.9.1
Summary: FutoIn Continuous Integration & Delivery Tool
Home-page: https://github.com/futoin/cid-tool
Download-URL: https://github.com/futoin/cid-tool/archive/master.zip
Author: Andrey Galkin
Author-email: andrey@futoin.org
License: Apache 2.0
Keywords: php ruby node nodejs npm gem rvm nvm grunt gulp bower  puppet build deploy futoin cmake make gradle maven java composer bundler
Classifier: Development Status :: 5 - Production/Stable
Classifier: Environment :: Console
Classifier: Intended Audience :: Developers
Classifier: Intended Audience :: Information Technology
Classifier: Intended Audience :: System Administrators
Classifier: License :: OSI Approved :: Apache Software License
Classifier: Natural Language :: English
Classifier: Programming Language :: C
Classifier: Programming Language :: C++
Classifier: Programming Language :: Java
Classifier: Programming Language :: JavaScript
Classifier: Programming Language :: Other
Classifier: Programming Language :: PHP
Classifier: Programming Language :: Python :: 3
Classifier: Programming Language :: Python :: 3.3
Classifier: Programming Language :: Python :: 3.4
Classifier: Programming Language :: Python :: 3.5
Classifier: Programming Language :: Python :: 3.6
Classifier: Programming Language :: Python :: 3.7
Classifier: Programming Language :: Python :: 3.8
Classifier: Programming Language :: Python :: 3.9
Classifier: Programming Language :: Ruby
Classifier: Programming Language :: Unix Shell
Classifier: Topic :: Software Development :: Build Tools
Classifier: Topic :: System :: Installation/Setup
Classifier: Topic :: Utilities
Requires-Python: >=3.3
License-File: LICENSE
Requires-Dist: docopt
Requires-Dist: requests (>=2.5.2)
Requires-Dist: urllib3 (>=1.21.1)
Requires-Dist: distro
Provides-Extra: test
Requires-Dist: nose ; extra == 'test'
